tractor/__init__.py
tractor/_actor.py
tractor/_broadcast.py
tractor/_child.py
tractor/_clustering.py
tractor/_debug.py
tractor/_discovery.py
tractor/_entry.py
tractor/_exceptions.py
tractor/_forkserver_override.py
tractor/_ipc.py
tractor/_messages.py
tractor/_mp_fixup_main.py
tractor/_portal.py
tractor/_root.py
tractor/_spawn.py
tractor/_state.py
tractor/_streaming.py
tractor/_supervise.py
tractor/_trionics.py
tractor/log.py
tractor/msg.py
tractor/testing/__init__.py
tractor/testing/_tractor_test.py
tractor/trionics/__init__.py
tractor/trionics/_broadcast.py
tractor/trionics/_mngrs.py
tractor-0.1.0a3.dist-info/LICENSE
tractor-0.1.0a3.dist-info/METADATA
tractor-0.1.0a3.dist-info/WHEEL
tractor-0.1.0a3.dist-info/top_level.txt
tractor-0.1.0a3.dist-info/RECORD
