Metadata-Version: 2.1
Name: tractor
Version: 0.1.0a3
Summary: structured concurrrent "actors"
Home-page: https://github.com/goodboy/tractor
Author: Tyler Goodlet
Maintainer: Tyler Goodlet
Maintainer-email: jgbt@protonmail.com
License: GPLv3
Keywords: trio,async,concurrency,actor model,distributed,multiprocessing
Platform: linux
Platform: windows
Classifier: Development Status :: 3 - Alpha
Classifier: Operating System :: POSIX :: Linux
Classifier: Operating System :: Microsoft :: Windows
Classifier: Framework :: Trio
Classifier: License :: OSI Approved :: GNU General Public License v3 or later (GPLv3+)
Classifier: Programming Language :: Python :: Implementation :: CPython
Classifier: Programming Language :: Python :: 3 :: Only
Classifier: Programming Language :: Python :: 3.8
Classifier: Programming Language :: Python :: 3.9
Classifier: Intended Audience :: Science/Research
Classifier: Intended Audience :: Developers
Classifier: Topic :: System :: Distributed Computing
Requires-Python: >=3.8
License-File: LICENSE
Requires-Dist: trio (>0.8)
Requires-Dist: async-generator
Requires-Dist: trio-typing
Requires-Dist: tricycle
Requires-Dist: colorlog
Requires-Dist: wrapt
Requires-Dist: pdbpp
Requires-Dist: msgpack
Provides-Extra: msgspec
Requires-Dist: msgspec (>=0.3.2') ; (python_version >= "3.9") and extra == 'msgspec'
